LICENSE
MANIFEST.in
README.rst
pyproject.toml
setup.py
whirlwind/__init__.py
whirlwind/_pytest.py
whirlwind/commander.py
whirlwind/server.py
whirlwind/store.py
whirlwind/version.py
whirlwind/request_handlers/__init__.py
whirlwind/request_handlers/base.py
whirlwind/request_handlers/command.py
whirlwind_web.egg-info/PKG-INFO
whirlwind_web.egg-info/SOURCES.txt
whirlwind_web.egg-info/dependency_links.txt
whirlwind_web.egg-info/entry_points.txt
whirlwind_web.egg-info/requires.txt
whirlwind_web.egg-info/top_level.txt