Metadata-Version: 2.1
Name: whirlwind-web
Version: 0.11.0
Summary: Wrapper around the tornado web server library
Home-page: http://github.com/delfick/whirlwind
Author: Stephen Moore
Author-email: delfick755@gmail.com
License: MIT
Keywords: tornado web
Platform: UNKNOWN
Provides-Extra: tests
Provides-Extra: peer
